Workbook

Sheet Cover
B2: Asian Paints - Fresh 3 Statement Model, DCF and Valuation
B5: Company | C5: Asian Paints Ltd
B6: Source | C6: AsianPaints.xlsx Screener export
B7: Units | C7: INR Cr, except per-share data
B8: Method | C8: Fresh workbook generated by Python; TCS is style reference only
B9: Current Price | C9: 2684.3
B10: Market Cap | C10: 257477.41
B11: Shares Outstanding | C11: 95.919759
B14: Workbook Flow
B15: Historical Data
B16: Income Statement
B17: Balance Sheet
B18: Cash Flow Statement
B19: Forecast Assumptions
B20: 3 Statement Model
B21: DCF Valuation
B22: Sensitivity
B23: Checks

Sheet Historical Data
B2: Asian Paints - Historical Data
B4: Profit & Loss
B5: INR Cr | C5: 42825 | D5: 43190 | E5: 43555 | F5: 43921 | G5: 44286 | H5: 44651 | I5: 45016 | J5: 45382 | K5: 45747 | L5: 46112
B6: Sales | C6: 15061.99 | D6: 16824.55 | E6: 19240.13 | F6: 20211.25 | G6: 21712.79 | H6: 29101.28 | I6: 34488.59 | J6: 35494.73 | K6: 33905.62 | L6: 35583.54
B7: Raw Material Cost | C7: 7452.6 | D7: 8128.17 | E7: 9974.4 | F7: 9981.99 | G7: 10425.55 | H7: 17123.25 | I7: 18985.53 | J7: 17410.84 | K7: 17504.51 | L7: 17142.01
B8: Change in Inventory | C8: 528.6 | D8: -142.13 | E8: 293.26 | F8: 239.15 | G8: 92.45 | H8: 1324.97 | I8: 309.73 | J8: -363.8 | K8: 205 | L8: -603.68
B9: Power and Fuel | C9: 106.02 | D9: 110.3 | E9: 119.63 | F9: 97.79 | G9: 86.05 | H9: 117.23 | I9: 138.29 | J9: 133.25 | K9: 148.58 | L9: 167.1
B10: Other Mfr. Exp | C10: 1662.75 | D10: 1691.68 | E10: 1862.35 | F10: 1946.12 | G10: 2068.31 | H10: 2880.45 | I10: 2916.2 | J10: 2767.18 | K10: 2687.4 | L10: 2767.11
B11: Employee Cost | C11: 1039.89 | D11: 1121.89 | E11: 1242.69 | F11: 1371.27 | G11: 1547.61 | H11: 1794.61 | I11: 2036.41 | J11: 2334.92 | K11: 2605.78 | L11: 2809.73
B12: Selling and Admin | C12: 4364.04 | D12: 2254.92 | E12: 2366.87 | F12: 2311.51 | G12: 2245.69 | H12: 2941.98 | I12: 3500.84 | J12: 3811.86 | K12: 3874.94 | L12: 4112.07
B13: Other Expenses | C13: -2028.47 | D13: 171.45 | E13: 202.51 | F13: 579.95 | G13: 576.43 | H13: 765.12 | I13: 961.21 | J13: 1087.9 | K13: 1283.2 | L13: 1282.11
B14: Other Income | C14: 337.9 | D14: 336.41 | E14: 273.77 | F14: 350.1 | G14: 331.65 | H14: 295.88 | I14: 431.46 | J14: 820.96 | K14: 350.22 | L14: 727.97
B15: Depreciation | C15: 334.79 | D15: 360.47 | E15: 622.14 | F15: 780.5 | G15: 791.27 | H15: 816.36 | I15: 858.02 | J15: 853 | K15: 1026.34 | L15: 1228.85
B16: Interest | C16: 37.33 | D16: 41.47 | E16: 110.47 | F16: 102.33 | G16: 91.63 | H16: 95.41 | I16: 144.45 | J16: 205.17 | K16: 227.02 | L16: 195.41
... B20: Dividend | C20: 987.98 | D20: 834.5 | E20: 1007.16 | F20: 1151.04 | G20: 1712.17 | H20: 1836.87 | I20: 2460.35 | J20: 3194.14 | K20: 2378.82 | L20: 2637.8
B23: Balance Sheet
B24: INR Cr | C24: 42825 | D24: 43190 | E24: 43555 | F24: 43921 | G24: 44286 | H24: 44651 | I24: 45016 | J24: 45382 | K24: 45747 | L24: 46112
B25: Equity Share Capital | C25: 95.92 | D25: 95.92 | E25: 95.92 | F25: 95.92 | G25: 95.92 | H25: 95.92 | I25: 95.92 | J25: 95.92 | K25: 95.92 | L25: 95.92
B26: Reserves | C26: 7507.97 | D26: 8314.31 | E26: 9374.63 | F26: 10034.24 | G26: 12710.37 | H26: 13715.64 | I26: 15896.31 | J26: 18632.38 | K26: 19303.89 | L26: 21275.67
B27: Borrowings | C27: 560.34 | D27: 533.43 | E27: 1319.6 | F27: 1118.5 | G27: 1093.12 | H27: 1586.88 | I27: 1932.62 | J27: 2474.38 | K27: 2290.29 | L27: 3928.93
B28: Other Liabilities | C28: 4240.96 | D28: 4819.82 | E28: 5458.69 | F28: 4889.31 | G28: 6455.93 | H28: 7559.99 | I28: 7854.48 | J28: 8698.09 | K28: 8665.15 | L28: 9218.23
B29: Total Liabilities | C29: 12405.19 | D29: 13763.48 | E29: 16248.84 | F29: 16137.97 | G29: 20355.34 | H29: 22958.43 | I29: 25779.33 | J29: 29900.77 | K29: 30355.25 | L29: 34518.75
B30: Net Block | C30: 3303.74 | D30: 3732.24 | E30: 6496.56 | F30: 6272.31 | G30: 5858.52 | H30: 5519.06 | I30: 5770.46 | J30: 7146.62 | K30: 9220.1 | L30: 9640.28
B31: CWIP | C31: 257.54 | D31: 1405.11 | E31: 209.67 | F31: 140.24 | G31: 182.98 | H31: 426.43 | I31: 1019.59 | J31: 2698.37 | K31: 1254.49 | L31: 1848.67
B32: Investments | C32: 2651.99 | D32: 2140.7 | E32: 2568.58 | F32: 2018.85 | G32: 4736.8 | H32: 3247.53 | I32: 4261.71 | J32: 4587.92 | K32: 4724.75 | L32: 7061.74
B33: Other Assets | C33: 6191.92 | D33: 6485.43 | E33: 6974.03 | F33: 7706.57 | G33: 9577.04 | H33: 13765.41 | I33: 14727.57 | J33: 15467.86 | K33: 15155.91 | L33: 15968.06
B34: Total Assets | C34: 12405.19 | D34: 13763.48 | E34: 16248.84 | F34: 16137.97 | G34: 20355.34 | H34: 22958.43 | I34: 25779.33 | J34: 29900.77 | K34: 30355.25 | L34: 34518.75
B35: Receivables | C35: 1446.6 | D35: 1730.63 | E35: 1907.33 | F35: 1795.22 | G35: 2602.17 | H35: 3871.44 | I35: 4636.94 | J35: 4889.05 | K35: 4313.65 | L35: 4461.8
B36: Inventory | C36: 2626.94 | D36: 2658.31 | E36: 3149.86 | F36: 3389.81 | G36: 3798.6 | H36: 6152.98 | I36: 6210.64 | J36: 5923.41 | K36: 6719.27 | L36: 5743.69
B39: Cash Flow
B40: INR Cr | C40: 42825 | D40: 43190 | E40: 43555 | F40: 43921 | G40: 44286 | H40: 44651 | I40: 45016 | J40: 45382 | K40: 45747 | L40: 46112
B41: CFO | C41: 1527.33 | D41: 2113.44 | E41: 2469.54 | F41: 3038.15 | G41: 3683.35 | H41: 986.49 | I41: 4193.43 | J41: 6103.6 | K41: 4423.96 | L41: 7088.18
B42: CFI | C42: -681.11 | D42: -1556.14 | E42: -917.79 | F42: -517.91 | G42: -540.54 | H42: -316.75 | I42: -1282.34 | J42: -2548.48 | K42: -940.91 | L42: -1328.23
B43: CFF | C43: -756.43 | D43: -1379.14 | E43: -1117.46 | F43: -2871.46 | G43: -650.4 | H43: -1807.61 | I43: -2140.05 | J43: -2982.5 | K43: -3752.58 | L43: -2376.51
B44: Net Cash Flow | C44: 89.79 | D44: -821.84 | E44: 434.29 | F44: -351.22 | G44: 2492.41 | H44: -1137.87 | I44: 771.04 | J44: 572.62 | K44: -269.53 | L44: 3383.44

Sheet Income Statement
A2: Asian Paints - Income Statement
A4: INR Cr | B4: 42825 | C4: 43190 | D4: 43555 | E4: 43921 | F4: 44286 | G4: 44651 | H4: 45016 | I4: 45382 | J4: 45747 | K4: 46112 | L4: FY1E | M4: FY2E | N4: FY3E | O4: FY4E | P4: FY5E
A6: Sales | B6: 15061.99 | C6: 16824.55 | D6: 19240.13 | E6: 20211.25 | F6: 21712.79 | G6: 29101.28 | H6: 34488.59 | I6: 35494.73 | J6: 33905.62 | K6: 35583.54 | L6: =K6*(1+'Forecast Assumptions'!$B$6) -> 35956.195 | M6: =L6*(1+'Forecast Assumptions'!$B$6) -> 36332.752 | N6: =M6*(1+'Forecast Assumptions'!$B$6) -> 36713.253 | O6: =N6*(1+'Forecast Assumptions'!$B$6) -> 37097.738 | P6: =O6*(1+'Forecast Assumptions'!$B$6) -> 37486.251
A7: Sales Growth | C7: =IFERROR(C6/B6-1,0) -> 0.11702039 | D7: =IFERROR(D6/C6-1,0) -> 0.14357472 | E7: =IFERROR(E6/D6-1,0) -> 0.050473671 | F7: =IFERROR(F6/E6-1,0) -> 0.074292288 | G7: =IFERROR(G6/F6-1,0) -> 0.34028285 | H7: =IFERROR(H6/G6-1,0) -> 0.18512278 | I7: =IFERROR(I6/H6-1,0) -> 0.029173127 | J7: =IFERROR(J6/I6-1,0) -> -0.044770308 | K7: =IFERROR(K6/J6-1,0) -> 0.049487961 | L7: =L6/K6-1 -> 0.010472667 | M7: =M6/L6-1 -> 0.010472667 | N7: =N6/M6-1 -> 0.010472667 | O7: =O6/N6-1 -> 0.010472667 | P7: =P6/O6-1 -> 0.010472667
A9: Raw Material Cost | B9: 7452.6 | C9: 8128.17 | D9: 9974.4 | E9: 9981.99 | F9: 10425.55 | G9: 17123.25 | H9: 18985.53 | I9: 17410.84 | J9: 17504.51 | K9: 17142.01
A10: Change in Inventory | B10: 528.6 | C10: -142.13 | D10: 293.26 | E10: 239.15 | F10: 92.45 | G10: 1324.97 | H10: 309.73 | I10: -363.8 | J10: 205 | K10: -603.68
A11: Power and Fuel | B11: 106.02 | C11: 110.3 | D11: 119.63 | E11: 97.79 | F11: 86.05 | G11: 117.23 | H11: 138.29 | I11: 133.25 | J11: 148.58 | K11: 167.1
A12: Other Manufacturing Expense | B12: 1662.75 | C12: 1691.68 | D12: 1862.35 | E12: 1946.12 | F12: 2068.31 | G12: 2880.45 | H12: 2916.2 | I12: 2767.18 | J12: 2687.4 | K12: 2767.11
A13: Employee Cost | B13: 1039.89 | C13: 1121.89 | D13: 1242.69 | E13: 1371.27 | F13: 1547.61 | G13: 1794.61 | H13: 2036.41 | I13: 2334.92 | J13: 2605.78 | K13: 2809.73
A14: Selling and Admin | B14: 4364.04 | C14: 2254.92 | D14: 2366.87 | E14: 2311.51 | F14: 2245.69 | G14: 2941.98 | H14: 3500.84 | I14: 3811.86 | J14: 3874.94 | K14: 4112.07
A15: Other Expenses | B15: -2028.47 | C15: 171.45 | D15: 202.51 | E15: 579.95 | F15: 576.43 | G15: 765.12 | H15: 961.21 | I15: 1087.9 | J15: 1283.2 | K15: 1282.11
A16: Total Operating Expenses | B16: =SUM(B9:B15) -> 13125.43 | C16: =SUM(C9:C15) -> 13336.28 | D16: =SUM(D9:D15) -> 16061.71 | E16: =SUM(E9:E15) -> 16527.78 | F16: =SUM(F9:F15) -> 17042.09 | G16: =SUM(G9:G15) -> 26947.61 | H16: =SUM(H9:H15) -> 28848.21 | I16: =SUM(I9:I15) -> 27182.15 | ... K16: =SUM(K9:K15) -> 27676.45 | L16: =L6-L21 -> 33290.77 | M16: =M6-M21 -> 33639.413 | N16: =N6-N21 -> 33991.707 | O16: =O6-O21 -> 34347.691 | P16: =P6-P21 -> 34707.403
A18: EBITDA | B18: =B6-B16+B20 -> 2271.35 | C18: =C6-C16+C20 -> 3848.74 | D18: =D6-D16+D20 -> 3800.56 | E18: =E6-E16+E20 -> 4463.97 | F18: =F6-F16+F20 -> 5461.97 | G18: =G6-G16+G20 -> 2970.03 | H18: =H6-H16+H20 -> 6498.4 | I18: =I6-I16+I20 -> 9165.58 | ... K18: =K6-K16+K20 -> 9135.94 | L18: =L21+L20 -> 2862.8813 | M18: =M21+M20 -> 2892.8633 | N18: =N21+N20 -> 2923.1593 | O18: =O21+O20 -> 2953.7725 | P18: =P21+P20 -> 2984.7064
A19: EBITDA Margin | B19: =IFERROR(B18/B6,0) -> 0.15080013 | C19: =IFERROR(C18/C6,0) -> 0.22875738 | D19: =IFERROR(D18/D6,0) -> 0.19753297 | E19: =IFERROR(E18/E6,0) -> 0.22086561 | F19: =IFERROR(F18/F6,0) -> 0.25155542 | G19: =IFERROR(G18/G6,0) -> 0.1020584 | H19: =IFERROR(H18/H6,0) -> 0.18842174 | I19: =IFERROR(I18/I6,0) -> 0.25822369 | ... P19: =IFERROR(P18/P6,0) -> 0.079621364
A20: Depreciation | B20: 334.79 | C20: 360.47 | D20: 622.14 | E20: 780.5 | F20: 791.27 | G20: 816.36 | H20: 858.02 | I20: 853 | J20: 1026.34 | K20: 1228.85 | L20: =L6*'Forecast Assumptions'!$B$9 -> 197.45646 | M20: =M6*'Forecast Assumptions'!$B$9 -> 199.52436 | N20: =N6*'Forecast Assumptions'!$B$9 -> 201.61391 | O20: =O6*'Forecast Assumptions'!$B$9 -> 203.72535 | P20: =P6*'Forecast Assumptions'!$B$9 -> 205.8589
A21: EBIT | B21: =B18-B20 -> 1936.56 | C21: =C18-C20 -> 3488.27 | D21: =D18-D20 -> 3178.42 | E21: =E18-E20 -> 3683.47 | F21: =F18-F20 -> 4670.7 | G21: =G18-G20 -> 2153.67 | H21: =H18-H20 -> 5640.38 | I21: =I18-I20 -> 8312.58 | ... K21: =K18-K20 -> 7907.09 | L21: =L6*'Forecast Assumptions'!$B$7 -> 2665.4248 | M21: =M6*'Forecast Assumptions'!$B$7 -> 2693.3389 | N21: =N6*'Forecast Assumptions'!$B$7 -> 2721.5454 | O21: =O6*'Forecast Assumptions'!$B$7 -> 2750.0472 | P21: =P6*'Forecast Assumptions'!$B$7 -> 2778.8475
A22: EBIT Margin | B22: =IFERROR(B21/B6,0) -> 0.12857265 | C22: =IFERROR(C21/C6,0) -> 0.20733214 | D22: =IFERROR(D21/D6,0) -> 0.16519743 | E22: =IFERROR(E21/E6,0) -> 0.1822485 | F22: =IFERROR(F21/F6,0) -> 0.21511284 | G22: =IFERROR(G21/G6,0) -> 0.074006023 | H22: =IFERROR(H21/H6,0) -> 0.16354336 | I22: =IFERROR(I21/I6,0) -> 0.23419195 | ... P22: =IFERROR(P21/P6,0) -> 0.07412978
A24: Other Income | B24: 337.9 | C24: 336.41 | D24: 273.77 | E24: 350.1 | F24: 331.65 | G24: 295.88 | H24: 431.46 | I24: 820.96 | J24: 350.22 | K24: 727.97 | L24: 0 | M24: 0 | N24: 0 | O24: 0 | P24: 0
A25: Interest | B25: 37.33 | C25: 41.47 | D25: 110.47 | E25: 102.33 | F25: 91.63 | G25: 95.41 | H25: 144.45 | I25: 205.17 | J25: 227.02 | K25: 195.41 | L25: 0 | M25: 0 | N25: 0 | O25: 0 | P25: 0
A26: Profit Before Tax | B26: 2959.54 | C26: 3138.48 | D26: 3306.1 | E26: 3629.04 | F26: 4304.35 | G26: 4187.72 | H26: 5688.83 | I26: 7347.77 | J26: 5103.07 | K26: 6003.44 | L26: =L21+L24-L25 -> 2665.4248 | M26: =M21+M24-M25 -> 2693.3389 | N26: =N21+N24-N25 -> 2721.5454 | O26: =O21+O24-O25 -> 2750.0472 | P26: =P21+P24-P25 -> 2778.8475
A27: Tax | B27: 943.29 | C27: 1040.96 | D27: 1098.06 | E27: 854.85 | F27: 1097.6 | G27: 1102.91 | H27: 1493.5 | I27: 1790.08 | J27: 1393.36 | K27: 1608.75 | L27: =L26*'Forecast Assumptions'!$B$8 -> 7166.3684 | M27: =M26*'Forecast Assumptions'!$B$8 -> 7241.4194 | N27: =N26*'Forecast Assumptions'!$B$8 -> 7317.2564 | O27: =O26*'Forecast Assumptions'!$B$8 -> 7393.8876 | P27: =P26*'Forecast Assumptions'!$B$8 -> 7471.3213
A28: Tax Rate | B28: =IFERROR(B27/B26,0) -> 0.31872859 | C28: =IFERROR(C27/C26,0) -> 0.33167648 | D28: =IFERROR(D27/D26,0) -> 0.33213151 | E28: =IFERROR(E27/E26,0) -> 0.23555816 | F28: =IFERROR(F27/F26,0) -> 0.25499785 | G28: =IFERROR(G27/G26,0) -> 0.26336766 | H28: =IFERROR(H27/H26,0) -> 0.26253201 | I28: =IFERROR(I27/I26,0) -> 0.24362221 | ... P28: =IFERROR(P27/P26,0) -> 2.6886402
A29: Net Profit | B29: 1939.43 | C29: 2038.93 | D29: 2155.92 | E29: 2705.17 | F29: 3139.29 | G29: 3030.57 | H29: 4106.45 | I29: 5460.23 | J29: 3667.23 | K29: 4325.35 | L29: =L26-L27 -> -4500.9436 | M29: =M26-M27 -> -4548.0805 | N29: =N26-N27 -> -4595.711 | O29: =O26-O27 -> -4643.8404 | P29: =P26-P27 -> -4692.4738
A30: Net Margin | B30: =IFERROR(B29/B6,0) -> 0.1287632 | C30: =IFERROR(C29/C6,0) -> 0.12118779 | D30: =IFERROR(D29/D6,0) -> 0.1120533 | E30: =IFERROR(E29/E6,0) -> 0.13384476 | F30: =IFERROR(F29/F6,0) -> 0.14458252 | G30: =IFERROR(G29/G6,0) -> 0.10413872 | H30: =IFERROR(H29/H6,0) -> 0.11906691 | I30: =IFERROR(I29/I6,0) -> 0.15383213 | ... P30: =IFERROR(P29/P6,0) -> -0.12517853
A31: EPS | B31: =IFERROR(B29/'Forecast Assumptions'!$B$17,0) -> 20.219296 | C31: =IFERROR(C29/'Forecast Assumptions'!$B$17,0) -> 21.256621 | D31: =IFERROR(D29/'Forecast Assumptions'!$B$17,0) -> 22.476287 | E31: =IFERROR(E29/'Forecast Assumptions'!$B$17,0) -> 28.202427 | F31: =IFERROR(F29/'Forecast Assumptions'!$B$17,0) -> 32.728293 | G31: =IFERROR(G29/'Forecast Assumptions'!$B$17,0) -> 31.594846 | H31: =IFERROR(H29/'Forecast Assumptions'!$B$17,0) -> 42.811304 | I31: =IFERROR(I29/'Forecast Assumptions'!$B$17,0) -> 56.924976 | ... P31: =IFERROR(P29/'Forecast Assumptions'!$B$17,0) -> -48.920825

Sheet Balance Sheet
A2: Asian Paints - Balance Sheet
A4: INR Cr | B4: 42825 | C4: 43190 | D4: 43555 | E4: 43921 | F4: 44286 | G4: 44651 | H4: 45016 | I4: 45382 | J4: 45747 | K4: 46112 | L4: FY1E | M4: FY2E | N4: FY3E | O4: FY4E | P4: FY5E
A6: Equity Share Capital | B6: 95.92 | C6: 95.92 | D6: 95.92 | E6: 95.92 | F6: 95.92 | G6: 95.92 | H6: 95.92 | I6: 95.92 | J6: 95.92 | K6: 95.92 | L6: =K6 -> 95.92 | M6: =L6 -> 95.92 | N6: =M6 -> 95.92 | O6: =N6 -> 95.92 | P6: =O6 -> 95.92
A7: Reserves | B7: 7507.97 | C7: 8314.31 | D7: 9374.63 | E7: 10034.24 | F7: 12710.37 | G7: 13715.64 | H7: 15896.31 | I7: 18632.38 | J7: 19303.89 | K7: 21275.67 | L7: =K7+'Income Statement'!L29 -> 16774.726 | M7: =L7+'Income Statement'!M29 -> 12226.646 | N7: =M7+'Income Statement'!N29 -> 7630.9349 | O7: =N7+'Income Statement'!O29 -> 2987.0945 | P7: =O7+'Income Statement'!P29 -> -1705.3792
A8: Borrowings | B8: 560.34 | C8: 533.43 | D8: 1319.6 | E8: 1118.5 | F8: 1093.12 | G8: 1586.88 | H8: 1932.62 | I8: 2474.38 | J8: 2290.29 | K8: 3928.93 | L8: =K8 -> 3928.93 | M8: =L8 -> 3928.93 | N8: =M8 -> 3928.93 | O8: =N8 -> 3928.93 | P8: =O8 -> 3928.93
A9: Other Liabilities | B9: 4240.96 | C9: 4819.82 | D9: 5458.69 | E9: 4889.31 | F9: 6455.93 | G9: 7559.99 | H9: 7854.48 | I9: 8698.09 | J9: 8665.15 | K9: 9218.23 | L9: =K9 -> 9218.23 | M9: =L9 -> 9218.23 | N9: =M9 -> 9218.23 | O9: =N9 -> 9218.23 | P9: =O9 -> 9218.23
A10: Total Liabilities | B10: 12405.19 | C10: 13763.48 | D10: 16248.84 | E10: 16137.97 | F10: 20355.34 | G10: 22958.43 | H10: 25779.33 | I10: 29900.77 | J10: 30355.25 | K10: 34518.75 | L10: =SUM(L6:L9) -> 30017.806 | M10: =SUM(M6:M9) -> 25469.726 | N10: =SUM(N6:N9) -> 20874.015 | O10: =SUM(O6:O9) -> 16230.175 | P10: =SUM(P6:P9) -> 11537.701
A12: Net Block | B12: 3303.74 | C12: 3732.24 | D12: 6496.56 | E12: 6272.31 | F12: 5858.52 | G12: 5519.06 | H12: 5770.46 | I12: 7146.62 | J12: 9220.1 | K12: 9640.28 | L12: =K12+'Income Statement'!L20 -> 9837.7365 | M12: =L12+'Income Statement'!M20 -> 10037.261 | N12: =M12+'Income Statement'!N20 -> 10238.875 | O12: =N12+'Income Statement'!O20 -> 10442.6 | P12: =O12+'Income Statement'!P20 -> 10648.459
A13: Capital Work in Progress | B13: 257.54 | C13: 1405.11 | D13: 209.67 | E13: 140.24 | F13: 182.98 | G13: 426.43 | H13: 1019.59 | I13: 2698.37 | J13: 1254.49 | K13: 1848.67 | L13: =K13 -> 1848.67 | M13: =L13 -> 1848.67 | N13: =M13 -> 1848.67 | O13: =N13 -> 1848.67 | P13: =O13 -> 1848.67
A14: Investments | B14: 2651.99 | C14: 2140.7 | D14: 2568.58 | E14: 2018.85 | F14: 4736.8 | G14: 3247.53 | H14: 4261.71 | I14: 4587.92 | J14: 4724.75 | K14: 7061.74 | L14: =K14 -> 7061.74 | M14: =L14 -> 7061.74 | N14: =M14 -> 7061.74 | O14: =N14 -> 7061.74 | P14: =O14 -> 7061.74
A15: Other Assets | B15: 6191.92 | C15: 6485.43 | D15: 6974.03 | E15: 7706.57 | F15: 9577.04 | G15: 13765.41 | H15: 14727.57 | I15: 15467.86 | J15: 15155.91 | K15: 15968.06 | L15: =L10-SUM(L12:L14) -> 11269.66 | M15: =M10-SUM(M12:M14) -> 6522.0551 | N15: =N10-SUM(N12:N14) -> 1724.7302 | O15: =O10-SUM(O12:O14) -> -3122.8356 | P15: =P10-SUM(P12:P14) -> -8021.1682
A16: Total Assets | B16: 12405.19 | C16: 13763.48 | D16: 16248.84 | E16: 16137.97 | F16: 20355.34 | G16: 22958.43 | H16: 25779.33 | I16: 29900.77 | J16: 30355.25 | K16: 34518.75 | L16: =SUM(L12:L15) -> 30017.806 | M16: =SUM(M12:M15) -> 25469.726 | N16: =SUM(N12:N15) -> 20874.015 | O16: =SUM(O12:O15) -> 16230.175 | P16: =SUM(P12:P15) -> 11537.701
A18: Receivables | B18: 1446.6 | C18: 1730.63 | D18: 1907.33 | E18: 1795.22 | F18: 2602.17 | G18: 3871.44 | H18: 4636.94 | I18: 4889.05 | J18: 4313.65 | K18: 4461.8 | L18: =K18*('Income Statement'!L6/'Income Statement'!K6) -> 4508.5269 | M18: =L18*('Income Statement'!M6/'Income Statement'!L6) -> 4555.7433 | N18: =M18*('Income Statement'!N6/'Income Statement'!M6) -> 4603.454 | O18: =N18*('Income Statement'!O6/'Income Statement'!N6) -> 4651.6645 | P18: =O18*('Income Statement'!P6/'Income Statement'!O6) -> 4700.3798
A19: Inventory | B19: 2626.94 | C19: 2658.31 | D19: 3149.86 | E19: 3389.81 | F19: 3798.6 | G19: 6152.98 | H19: 6210.64 | I19: 5923.41 | J19: 6719.27 | K19: 5743.69 | L19: =K19*('Income Statement'!L6/'Income Statement'!K6) -> 5803.8418 | M19: =L19*('Income Statement'!M6/'Income Statement'!L6) -> 5864.6235 | N19: =M19*('Income Statement'!N6/'Income Statement'!M6) -> 5926.0417 | O19: =N19*('Income Statement'!O6/'Income Statement'!N6) -> 5988.1032 | P19: =O19*('Income Statement'!P6/'Income Statement'!O6) -> 6050.8146
A20: Balance Check | B20: =B16-B10 -> 0 | C20: =C16-C10 -> 0 | D20: =D16-D10 -> 0 | E20: =E16-E10 -> 0 | F20: =F16-F10 -> 0 | G20: =G16-G10 -> 0 | H20: =H16-H10 -> 0 | I20: =I16-I10 -> 0 | ... P20: =P16-P10 -> 0

Sheet Cash Flow Statement
A2: Asian Paints - Cash Flow Statement
A4: INR Cr | B4: 42825 | C4: 43190 | D4: 43555 | E4: 43921 | F4: 44286 | G4: 44651 | H4: 45016 | I4: 45382 | J4: 45747 | K4: 46112 | L4: FY1E | M4: FY2E | N4: FY3E | O4: FY4E | P4: FY5E
A6: Net Income | B6: ='Income Statement'!B29 -> 1939.43 | C6: ='Income Statement'!C29 -> 2038.93 | D6: ='Income Statement'!D29 -> 2155.92 | E6: ='Income Statement'!E29 -> 2705.17 | F6: ='Income Statement'!F29 -> 3139.29 | G6: ='Income Statement'!G29 -> 3030.57 | H6: ='Income Statement'!H29 -> 4106.45 | I6: ='Income Statement'!I29 -> 5460.23 | ... P6: ='Income Statement'!P29 -> -4692.4738
A7: Depreciation | B7: ='Income Statement'!B20 -> 334.79 | C7: ='Income Statement'!C20 -> 360.47 | D7: ='Income Statement'!D20 -> 622.14 | E7: ='Income Statement'!E20 -> 780.5 | F7: ='Income Statement'!F20 -> 791.27 | G7: ='Income Statement'!G20 -> 816.36 | H7: ='Income Statement'!H20 -> 858.02 | I7: ='Income Statement'!I20 -> 853 | ... P7: ='Income Statement'!P20 -> 205.8589
A8: Change in Working Capital | B8: ='Cash Flow Statement'!B10-'Cash Flow Statement'!B6-'Cash Flow Statement'!B7 -> -746.89 | C8: ='Cash Flow Statement'!C10-'Cash Flow Statement'!C6-'Cash Flow Statement'!C7 -> -285.96 | D8: ='Cash Flow Statement'!D10-'Cash Flow Statement'!D6-'Cash Flow Statement'!D7 -> -308.52 | E8: ='Cash Flow Statement'!E10-'Cash Flow Statement'!E6-'Cash Flow Statement'!E7 -> -447.52 | F8: ='Cash Flow Statement'!F10-'Cash Flow Statement'!F6-'Cash Flow Statement'!F7 -> -247.21 | G8: ='Cash Flow Statement'!G10-'Cash Flow Statement'!G6-'Cash Flow Statement'!G7 -> -2860.44 | H8: ='Cash Flow Statement'!H10-'Cash Flow Statement'!H6-'Cash Flow Statement'!H7 -> -771.04 | I8: ='Cash Flow Statement'!I10-'Cash Flow Statement'!I6-'Cash Flow Statement'!I7 -> -209.63 | ... K8: ='Cash Flow Statement'!K10-'Cash Flow Statement'!K6-'Cash Flow Statement'!K7 -> 1533.98 | L8: =-('Income Statement'!L6-'Income Statement'!K6)*'Forecast Assumptions'!$B$10 -> -16.769456 | M8: =-('Income Statement'!M6-'Income Statement'!L6)*'Forecast Assumptions'!$B$10 -> -16.945077 | N8: =-('Income Statement'!N6-'Income Statement'!M6)*'Forecast Assumptions'!$B$10 -> -17.122537 | O8: =-('Income Statement'!O6-'Income Statement'!N6)*'Forecast Assumptions'!$B$10 -> -17.301856 | P8: =-('Income Statement'!P6-'Income Statement'!O6)*'Forecast Assumptions'!$B$10 -> -17.483052
A10: Cash from Operating Activity | B10: 1527.33 | C10: 2113.44 | D10: 2469.54 | E10: 3038.15 | F10: 3683.35 | G10: 986.49 | H10: 4193.43 | I10: 6103.6 | J10: 4423.96 | K10: 7088.18 | L10: =SUM(L6:L8) -> -4320.2566 | M10: =SUM(M6:M8) -> -4365.5012 | N10: =SUM(N6:N8) -> -4411.2196 | O10: =SUM(O6:O8) -> -4457.4169 | P10: =SUM(P6:P8) -> -4504.0979
A12: Cash from Investing Activity | B12: -681.11 | C12: -1556.14 | D12: -917.79 | E12: -517.91 | F12: -540.54 | G12: -316.75 | H12: -1282.34 | I12: -2548.48 | J12: -940.91 | K12: -1328.23 | L12: =-'Income Statement'!L6*'Forecast Assumptions'!$B$9 -> -197.45646 | M12: =-'Income Statement'!M6*'Forecast Assumptions'!$B$9 -> -199.52436 | N12: =-'Income Statement'!N6*'Forecast Assumptions'!$B$9 -> -201.61391 | O12: =-'Income Statement'!O6*'Forecast Assumptions'!$B$9 -> -203.72535 | P12: =-'Income Statement'!P6*'Forecast Assumptions'!$B$9 -> -205.8589
A13: Cash from Financing Activity | B13: -756.43 | C13: -1379.14 | D13: -1117.46 | E13: -2871.46 | F13: -650.4 | G13: -1807.61 | H13: -2140.05 | I13: -2982.5 | J13: -3752.58 | K13: -2376.51 | L13: 0 | M13: 0 | N13: 0 | O13: 0 | P13: 0
A15: Net Cash Flow | B15: 89.79 | C15: -821.84 | D15: 434.29 | E15: -351.22 | F15: 2492.41 | G15: -1137.87 | H15: 771.04 | I15: 572.62 | J15: -269.53 | K15: 3383.44 | L15: =SUM(L10,L12,L13) -> -4517.7131 | M15: =SUM(M10,M12,M13) -> -4565.0256 | N15: =SUM(N10,N12,N13) -> -4612.8336 | O15: =SUM(O10,O12,O13) -> -4661.1422 | P15: =SUM(P10,P12,P13) -> -4709.9568

Sheet Forecast Assumptions
A2: Asian Paints - Forecast Assumptions
A4: Assumption | B4: Value | C4: Formula / Basis | D4: Type
A5: Forecast years | B5: 5 | C5: Explicit forecast period | D5: Input
A6: Revenue growth | B6: =IFERROR(('Historical Data'!L6/'Historical Data'!I6)^(1/3)-1,0.08) -> 0.010472667 | C6: 3Y CAGR fallback | D6: Input
A7: EBIT margin | B7: =IFERROR('Historical Data'!L20/'Historical Data'!L6,0.18) -> 0.07412978 | C7: Latest EBIT / Sales | D7: Input
A8: Cash tax rate | B8: =IFERROR('Historical Data'!L19/'Historical Data'!L18,0.25) -> 2.6886402 | C8: Latest Tax / PBT | D8: Input
A9: D&A % Sales | B9: =IFERROR('Historical Data'!L16/'Historical Data'!L6,0.03) -> 0.005491584 | C9: Latest depreciation / Sales | D9: Input
A10: Capex % Sales | B10: 0.045 | C10: Editable estimate | D10: Input
A11: NWC % Incremental Sales | B11: 0.1 | C11: Editable estimate | D11: Input
A12: WACC | B12: 0.11 | C12: Editable DCF discount rate | D12: Input
A13: Terminal growth | B13: 0.045 | C13: Editable Gordon growth assumption | D13: Input
A14: Exit EV/EBITDA | B14: 35 | C14: Alternative valuation check | D14: Input
A15: Net debt / (cash) | B15: ='Historical Data'!L35 -> 4461.8 | C15: Latest borrowings from source | D15: Linked
A16: Current share price | B16: 2684.3 | C16: Screener export current price | D16: Source
A17: Shares outstanding | B17: 95.919759 | C17: Market cap / price | D17: Source

Sheet 3 Statement Model
A2: Asian Paints - 3 Statement Model Summary
A4: INR Cr | B4: 42825 | C4: 43190 | D4: 43555 | E4: 43921 | F4: 44286 | G4: 44651 | H4: 45016 | I4: 45382 | J4: 45747 | K4: 46112 | L4: FY1E | M4: FY2E | N4: FY3E | O4: FY4E | P4: FY5E
A6: Revenue | B6: ='Income Statement'!B6 -> 15061.99 | C6: ='Income Statement'!C6 -> 16824.55 | D6: ='Income Statement'!D6 -> 19240.13 | E6: ='Income Statement'!E6 -> 20211.25 | F6: ='Income Statement'!F6 -> 21712.79 | G6: ='Income Statement'!G6 -> 29101.28 | H6: ='Income Statement'!H6 -> 34488.59 | I6: ='Income Statement'!I6 -> 35494.73 | ... P6: ='Income Statement'!P6 -> 37486.251
A7: EBITDA | B7: ='Income Statement'!B18 -> 2271.35 | C7: ='Income Statement'!C18 -> 3848.74 | D7: ='Income Statement'!D18 -> 3800.56 | E7: ='Income Statement'!E18 -> 4463.97 | F7: ='Income Statement'!F18 -> 5461.97 | G7: ='Income Statement'!G18 -> 2970.03 | H7: ='Income Statement'!H18 -> 6498.4 | I7: ='Income Statement'!I18 -> 9165.58 | ... P7: ='Income Statement'!P18 -> 2984.7064
A8: EBIT | B8: ='Income Statement'!B21 -> 1936.56 | C8: ='Income Statement'!C21 -> 3488.27 | D8: ='Income Statement'!D21 -> 3178.42 | E8: ='Income Statement'!E21 -> 3683.47 | F8: ='Income Statement'!F21 -> 4670.7 | G8: ='Income Statement'!G21 -> 2153.67 | H8: ='Income Statement'!H21 -> 5640.38 | I8: ='Income Statement'!I21 -> 8312.58 | ... P8: ='Income Statement'!P21 -> 2778.8475
A9: Net Profit | B9: ='Income Statement'!B29 -> 1939.43 | C9: ='Income Statement'!C29 -> 2038.93 | D9: ='Income Statement'!D29 -> 2155.92 | E9: ='Income Statement'!E29 -> 2705.17 | F9: ='Income Statement'!F29 -> 3139.29 | G9: ='Income Statement'!G29 -> 3030.57 | H9: ='Income Statement'!H29 -> 4106.45 | I9: ='Income Statement'!I29 -> 5460.23 | ... P9: ='Income Statement'!P29 -> -4692.4738
A11: Total Assets | B11: ='Balance Sheet'!B16 -> 12405.19 | C11: ='Balance Sheet'!C16 -> 13763.48 | D11: ='Balance Sheet'!D16 -> 16248.84 | E11: ='Balance Sheet'!E16 -> 16137.97 | F11: ='Balance Sheet'!F16 -> 20355.34 | G11: ='Balance Sheet'!G16 -> 22958.43 | H11: ='Balance Sheet'!H16 -> 25779.33 | I11: ='Balance Sheet'!I16 -> 29900.77 | ... P11: ='Balance Sheet'!P16 -> 11537.701
A12: Total Liabilities | B12: ='Balance Sheet'!B10 -> 12405.19 | C12: ='Balance Sheet'!C10 -> 13763.48 | D12: ='Balance Sheet'!D10 -> 16248.84 | E12: ='Balance Sheet'!E10 -> 16137.97 | F12: ='Balance Sheet'!F10 -> 20355.34 | G12: ='Balance Sheet'!G10 -> 22958.43 | H12: ='Balance Sheet'!H10 -> 25779.33 | I12: ='Balance Sheet'!I10 -> 29900.77 | ... P12: ='Balance Sheet'!P10 -> 11537.701
A13: Balance Check | B13: ='Balance Sheet'!B20 -> 0 | C13: ='Balance Sheet'!C20 -> 0 | D13: ='Balance Sheet'!D20 -> 0 | E13: ='Balance Sheet'!E20 -> 0 | F13: ='Balance Sheet'!F20 -> 0 | G13: ='Balance Sheet'!G20 -> 0 | H13: ='Balance Sheet'!H20 -> 0 | I13: ='Balance Sheet'!I20 -> 0 | ... P13: ='Balance Sheet'!P20 -> 0
A15: CFO | B15: ='Cash Flow Statement'!B10 -> 1527.33 | C15: ='Cash Flow Statement'!C10 -> 2113.44 | D15: ='Cash Flow Statement'!D10 -> 2469.54 | E15: ='Cash Flow Statement'!E10 -> 3038.15 | F15: ='Cash Flow Statement'!F10 -> 3683.35 | G15: ='Cash Flow Statement'!G10 -> 986.49 | H15: ='Cash Flow Statement'!H10 -> 4193.43 | I15: ='Cash Flow Statement'!I10 -> 6103.6 | ... P15: ='Cash Flow Statement'!P10 -> -4504.0979
A16: CFI | B16: ='Cash Flow Statement'!B12 -> -681.11 | C16: ='Cash Flow Statement'!C12 -> -1556.14 | D16: ='Cash Flow Statement'!D12 -> -917.79 | E16: ='Cash Flow Statement'!E12 -> -517.91 | F16: ='Cash Flow Statement'!F12 -> -540.54 | G16: ='Cash Flow Statement'!G12 -> -316.75 | H16: ='Cash Flow Statement'!H12 -> -1282.34 | I16: ='Cash Flow Statement'!I12 -> -2548.48 | ... P16: ='Cash Flow Statement'!P12 -> -205.8589
A17: CFF | B17: ='Cash Flow Statement'!B13 -> -756.43 | C17: ='Cash Flow Statement'!C13 -> -1379.14 | D17: ='Cash Flow Statement'!D13 -> -1117.46 | E17: ='Cash Flow Statement'!E13 -> -2871.46 | F17: ='Cash Flow Statement'!F13 -> -650.4 | G17: ='Cash Flow Statement'!G13 -> -1807.61 | H17: ='Cash Flow Statement'!H13 -> -2140.05 | I17: ='Cash Flow Statement'!I13 -> -2982.5 | ... P17: ='Cash Flow Statement'!P13 -> 0
A18: Net Cash Flow | B18: ='Cash Flow Statement'!B15 -> 89.79 | C18: ='Cash Flow Statement'!C15 -> -821.84 | D18: ='Cash Flow Statement'!D15 -> 434.29 | E18: ='Cash Flow Statement'!E15 -> -351.22 | F18: ='Cash Flow Statement'!F15 -> 2492.41 | G18: ='Cash Flow Statement'!G15 -> -1137.87 | H18: ='Cash Flow Statement'!H15 -> 771.04 | I18: ='Cash Flow Statement'!I15 -> 572.62 | ... P18: ='Cash Flow Statement'!P15 -> -4709.9568

Sheet DCF Valuation
A2: Asian Paints - DCF Valuation
A4: INR Cr | B4: FY1E | C4: FY2E | D4: FY3E | E4: FY4E | F4: FY5E
A5: Revenue | B5: ='Income Statement'!L6 -> 35956.195 | C5: ='Income Statement'!M6 -> 36332.752 | D5: ='Income Statement'!N6 -> 36713.253 | E5: ='Income Statement'!O6 -> 37097.738 | F5: ='Income Statement'!P6 -> 37486.251
A6: EBIT | B6: ='Income Statement'!L21 -> 2665.4248 | C6: ='Income Statement'!M21 -> 2693.3389 | D6: ='Income Statement'!N21 -> 2721.5454 | E6: ='Income Statement'!O21 -> 2750.0472 | F6: ='Income Statement'!P21 -> 2778.8475
A7: Cash Taxes | B7: ='Income Statement'!L27 -> 7166.3684 | C7: ='Income Statement'!M27 -> 7241.4194 | D7: ='Income Statement'!N27 -> 7317.2564 | E7: ='Income Statement'!O27 -> 7393.8876 | F7: ='Income Statement'!P27 -> 7471.3213
A8: NOPAT | B8: =B6-B7 -> -4500.9436 | C8: =C6-C7 -> -4548.0805 | D8: =D6-D7 -> -4595.711 | E8: =E6-E7 -> -4643.8404 | F8: =F6-F7 -> -4692.4738
A9: D&A | B9: ='Income Statement'!L20 -> 197.45646 | C9: ='Income Statement'!M20 -> 199.52436 | D9: ='Income Statement'!N20 -> 201.61391 | E9: ='Income Statement'!O20 -> 203.72535 | F9: ='Income Statement'!P20 -> 205.8589
A10: Capex | B10: =-'Cash Flow Statement'!L12 -> 197.45646 | C10: =-'Cash Flow Statement'!M12 -> 199.52436 | D10: =-'Cash Flow Statement'!N12 -> 201.61391 | E10: =-'Cash Flow Statement'!O12 -> 203.72535 | F10: =-'Cash Flow Statement'!P12 -> 205.8589
A11: Change in NWC | B11: =-'Cash Flow Statement'!L8 -> 16.769456 | C11: =-'Cash Flow Statement'!M8 -> 16.945077 | D11: =-'Cash Flow Statement'!N8 -> 17.122537 | E11: =-'Cash Flow Statement'!O8 -> 17.301856 | F11: =-'Cash Flow Statement'!P8 -> 17.483052
A12: Unlevered FCF | B12: =B8+B9-B10-B11 -> -4517.7131 | C12: =C8+C9-C10-C11 -> -4565.0256 | D12: =D8+D9-D10-D11 -> -4612.8336 | E12: =E8+E9-E10-E11 -> -4661.1422 | F12: =F8+F9-F10-F11 -> -4709.9568
A13: Discount Period | B13: 1 | C13: 2 | D13: 3 | E13: 4 | F13: 5
A14: Discount Factor | B14: =1/(1+'Forecast Assumptions'!$B$12)^B13 -> 0.9009009 | C14: =1/(1+'Forecast Assumptions'!$B$12)^C13 -> 0.81162243 | D14: =1/(1+'Forecast Assumptions'!$B$12)^D13 -> 0.73119138 | E14: =1/(1+'Forecast Assumptions'!$B$12)^E13 -> 0.65873097 | F14: =1/(1+'Forecast Assumptions'!$B$12)^F13 -> 0.59345133
A15: PV of FCF | B15: =B12*B14 -> -4070.0118 | C15: =C12*C14 -> -3705.0772 | D15: =D12*D14 -> -3372.8641 | E15: =E12*E14 -> -3070.4388 | F15: =F12*F14 -> -2795.1301
A18: Valuation Bridge
A19: PV of FCF | B19: =SUM(B15:F15) -> -17013.522
A20: Terminal FCF | B20: =F12*(1+'Forecast Assumptions'!$B$13) -> -4921.9049
A21: Terminal Value | B21: =B20/('Forecast Assumptions'!$B$12-'Forecast Assumptions'!$B$13) -> -75721.614
A22: PV of Terminal Value | B22: =B21*F14 -> -44937.092
A23: Enterprise Value | B23: =B19+B22 -> -61950.614
A24: Less: Net Debt / (Cash) | B24: ='Forecast Assumptions'!$B$15 -> 4461.8
A25: Equity Value | B25: =B23-B24 -> -66412.414
A26: Shares Outstanding | B26: ='Forecast Assumptions'!$B$17 -> 95.919759
A27: Implied Value / Share | B27: =IF(B26>0,B25/B26,0) -> -692.37469
A28: Current Share Price | B28: ='Forecast Assumptions'!$B$16 -> 2684.3
A29: Upside / Downside | B29: =IF(B28>0,B27/B28-1,0) -> -1.2579349

Sheet Sensitivity
A2: Asian Paints - DCF Sensitivity
A4: Implied Value / Share Sensitivity
A6: WACC / Terminal Growth | B6: 0.035 | C6: 0.04 | D6: 0.045 | E6: 0.05 | F6: 0.055
A7: 0.095
A8: 0.105
A9: 0.11
A10: 0.115
A11: 0.125

Sheet Checks
A2: Asian Paints - Model Checks
A4: Check | B4: Actual | C4: Expected | D4: Difference | E4: Tolerance | F4: Status | G4: Notes
A5: Latest balance sheet balances | B5: ='Balance Sheet'!K16 -> 34518.75 | C5: ='Balance Sheet'!K10 -> 34518.75 | D5: =B5-C5 -> 0 | E5: 1 | F5: =IF(ABS(D5)<=E5,"OK","Check") -> OK | G5: Historical total assets should equal total liabilities.
A6: Forecast balance sheet balances | B6: ='Balance Sheet'!P16 -> 11537.701 | C6: ='Balance Sheet'!P10 -> 11537.701 | D6: =B6-C6 -> 0 | E6: 1 | F6: =IF(ABS(D6)<=E6,"OK","Check") -> OK | G6: Forecast other assets are used as balancing item.
A7: WACC exceeds terminal growth | B7: ='Forecast Assumptions'!B12 -> 0.11 | C7: ='Forecast Assumptions'!B13 -> 0.045 | D7: =B7-C7 -> 0.065 | E7: 0 | F7: =IF(B7>C7,"OK","Check") -> OK | G7: DCF terminal value requires WACC > terminal growth.
A8: Shares positive | B8: ='Forecast Assumptions'!B17 -> 95.919759 | C8: 0 | D8: =B8-C8 -> 95.919759 | E8: 0 | F8: =IF(B8>0,"OK","Check") -> OK | G8: Needed for per-share valuation.
A9: Overall model status | F9: =IF(COUNTIF(F5:F8,"Check")=0,"OK","Check") -> OK | G9: All checks should read OK.
